{
  "sections": {
    "54aeef54-77b5-4890-9ee2-722bfa718bde": {
      "type": "about-banner",
      "blocks": {
        "c01a47e3-6398-4986-9320-7ebb053d3126": {
          "type": "banner",
          "settings": {
            "image": "shopify:\/\/shop_images\/Peta-murgatroyd-peta-jane-beauty-self-tanning-bottle-square.jpg"
          }
        },
        "71e19f01-ff1d-4d9e-8b61-b55b6a18a7a9": {
          "type": "banner",
          "settings": {
            "image": "shopify:\/\/shop_images\/Peta-murgatroyd-sitting-fake-tan-square.jpg"
          }
        },
        "0bd29d51-bc2c-4b89-9cb7-b1787c711f66": {
          "type": "banner",
          "settings": {
            "image": "shopify:\/\/shop_images\/peta-murgatroyd-tanning-line.png"
          }
        }
      },
      "block_order": [
        "c01a47e3-6398-4986-9320-7ebb053d3126",
        "71e19f01-ff1d-4d9e-8b61-b55b6a18a7a9",
        "0bd29d51-bc2c-4b89-9cb7-b1787c711f66"
      ],
      "settings": {
        "padding_top": 10,
        "padding_bottom": 0
      }
    },
    "c3c78e33-012c-4202-a327-9595743ac291": {
      "type": "about-title-description",
      "settings": {
        "description": "<p><\/p>"
      }
    },
    "4e0dd795-8efb-4adc-bf2e-79ed6496850b": {
      "type": "video",
      "settings": {
        "heading": "",
        "heading_size": "h2",
        "cover_image": "shopify:\/\/shop_images\/peta-murgatroyd-with-her-self-tanning-products.jpg",
        "video_url": "https:\/\/www.youtube.com\/watch?v=_e76p-0NuZM",
        "description": "About Peta Jane Beauty Self Tanning Products",
        "full_width": false,
        "color_scheme": "background-1",
        "padding_top": 0,
        "padding_bottom": 0
      }
    },
    "3accb7d5-93fa-4bf8-92f6-92ce29932d02": {
      "type": "page-about",
      "blocks": {
        "efe288a3-0b41-4733-b857-63a79591395c": {
          "type": "present_block_image",
          "disabled": true,
          "settings": {
            "presentation_image": "shopify:\/\/shop_images\/about_presentation_img.png"
          }
        },
        "af8ece20-f93f-422a-a3f0-4ace9cd620f8": {
          "type": "present_block_numbers",
          "settings": {
            "presentation_number": "",
            "presentation_text": ""
          }
        },
        "0d4fe802-c3d0-4e53-a8f1-61c08be692a4": {
          "type": "present_block_numbers",
          "settings": {
            "presentation_number": "",
            "presentation_text": ""
          }
        },
        "ff52e932-9c5c-41a7-9474-a6400471f8af": {
          "type": "present_block_numbers",
          "settings": {
            "presentation_number": "",
            "presentation_text": ""
          }
        },
        "94d4f158-8987-4a33-81d9-8fbee5db3516": {
          "type": "present_block_numbers",
          "settings": {
            "presentation_number": "",
            "presentation_text": ""
          }
        },
        "b8101ad0-0457-49ac-888f-16326837e377": {
          "type": "present_block_note",
          "settings": {
            "presentation_note_icon": "shopify:\/\/shop_images\/about_presentation_note_icon_937d5bdf-7ff3-43d8-9cc3-428d1ae4e03e.png",
            "presentation_note_text": "<p>Peta Jane Murgatroyd is an internationally celebrated actress, dancer, and TV personality. Her commitment to a healthy lifestyle inspired her to develop products to help you look good and feel confident.<\/p>"
          }
        }
      },
      "block_order": [
        "efe288a3-0b41-4733-b857-63a79591395c",
        "af8ece20-f93f-422a-a3f0-4ace9cd620f8",
        "0d4fe802-c3d0-4e53-a8f1-61c08be692a4",
        "ff52e932-9c5c-41a7-9474-a6400471f8af",
        "94d4f158-8987-4a33-81d9-8fbee5db3516",
        "b8101ad0-0457-49ac-888f-16326837e377"
      ],
      "settings": {
        "padding_top": 4,
        "padding_bottom": 36
      }
    },
    "8c1fab66-6371-462f-b4f9-03175c7dee7f": {
      "type": "about-content",
      "settings": {
        "padding_top": 10,
        "padding_bottom": 10
      }
    },
    "3bf913e4-f548-4649-be9e-32f6f10fbac3": {
      "type": "inst-block",
      "settings": {
        "app": true,
        "title": "SHOP THE FEED",
        "subtitle": "GET THE LOOK",
        "marquee": "",
        "overlay_opacity": 0,
        "padding_top": 36,
        "padding_bottom": 36
      }
    }
  },
  "order": [
    "54aeef54-77b5-4890-9ee2-722bfa718bde",
    "c3c78e33-012c-4202-a327-9595743ac291",
    "4e0dd795-8efb-4adc-bf2e-79ed6496850b",
    "3accb7d5-93fa-4bf8-92f6-92ce29932d02",
    "8c1fab66-6371-462f-b4f9-03175c7dee7f",
    "3bf913e4-f548-4649-be9e-32f6f10fbac3"
  ]
}
